{
  "type": "FeatureCollection",
  "features": [
    {
      "type": "Feature",
      "properties": {},
      "geometry": {
        "type": "Polygon",
        "coordinates": [
          [
            [
              10.557861328125,
              59.06315402462662
            ],
            [
              7.778320312499999,
              57.94401445403342
            ],
            [
              7.03125,
              57.94401445403342
            ],
            [
              8.1243896484375,
              56.81892067431724
            ],
            [
              8.624267578125,
              57.180924749098736
            ],
            [
              9.129638671875,
              57.1958078966064
            ],
            [
              9.5361328125,
              57.26716357153586
            ],
            [
              9.964599609375,
              57.645400667406605
            ],
            [
              10.228271484374998,
              57.67478584938936
            ],
            [
              10.74462890625,
              57.81550367239279
            ],
            [
              11.414794921875,
              57.9760704482266
            ],
            [
              11.09619140625,
              58.530992912684546
            ],
            [
              11.05224609375,
              58.76250326278713
            ],
            [
              10.78857421875,
              59.06880155405589
            ],
            [
              10.557861328125,
              59.06315402462662
            ]
          ]
        ]
      }
    }
  ]
}